pyunlvrtm/__init__.py
pyunlvrtm/io.py
pyunlvrtm/setup.py
pyunlvrtm/util.py
pyunlvrtm-0.2.4.dist-info/DESCRIPTION.rst
pyunlvrtm-0.2.4.dist-info/METADATA
pyunlvrtm-0.2.4.dist-info/RECORD
pyunlvrtm-0.2.4.dist-info/WHEEL
pyunlvrtm-0.2.4.dist-info/metadata.json
pyunlvrtm-0.2.4.dist-info/top_level.txt
