Metadata-Version: 2.0
Name: pyunlvrtm
Version: 0.2.4
Summary: Python packages to faciliate the UNL-VRTM model
Home-page: https://github.com/xxu2/pyunlvrtm
Author: Richard Xu
Author-email: xxu@huksers.unl.edu
License: MIT
Platform: UNKNOWN
